autobiber/__init__.py
autobiber/_version.py
autobiber/autobiber.py
autobiber/utils.py
autobiber-0.0.3.dist-info/LICENSE
autobiber-0.0.3.dist-info/METADATA
autobiber-0.0.3.dist-info/WHEEL
autobiber-0.0.3.dist-info/entry_points.txt
autobiber-0.0.3.dist-info/top_level.txt
autobiber-0.0.3.dist-info/RECORD
