Metadata-Version: 2.1
Name: autobiber
Version: 0.0.3
Summary: A tool for find bibtex via dblp
Home-page: https://github.com/Yeba/autobiber
Author: yjliu
Author-email: yjliu045@stu.suda.edu.cn
Classifier: Programming Language :: Python :: 3
Classifier: License :: OSI Approved :: MIT License
Classifier: Operating System :: OS Independent
Requires-Python: >=3.6
License-File: LICENSE
Requires-Dist: argparse
Requires-Dist: fake-useragent
Requires-Dist: requests
Requires-Dist: urllib3
